xmindparser/__init__.py
xmindparser/main.py
xmindparser/xreader.py
xmindparser/zenreader.py
xmindparser-1.0.8.dist-info/METADATA
xmindparser-1.0.8.dist-info/RECORD
xmindparser-1.0.8.dist-info/WHEEL
xmindparser-1.0.8.dist-info/entry_points.txt
xmindparser-1.0.8.dist-info/top_level.txt
