Metadata-Version: 1.1
Name: xmindparser
Version: 1.0.8
Summary: Convert xmind to programmable data types, support xmind pro and xmind zen file types.
Home-page: https://github.com/tobyqin/xmindparser
Author: Toby Qin
Author-email: toby.qin@live.com
License: UNKNOWN
Keywords: xmind parser converter json xml
Platform: UNKNOWN
Classifier: License :: OSI Approved :: MIT License
Classifier: Topic :: Software Development
Classifier: Topic :: Utilities
Classifier: Operating System :: Microsoft :: Windows
Classifier: Operating System :: MacOS :: MacOS X
Classifier: Programming Language :: Python :: 3.4
Classifier: Programming Language :: Python :: 3.5
Classifier: Programming Language :: Python :: 3.6
Classifier: Programming Language :: Python :: 3.7
Classifier: Programming Language :: Python :: 3.8
